[
  {
    "package": "janitor",
    "url": "https://github.com/sfirke/janitor",
    "via": ["r2dii.physical.risk", "r2dii.utils"],
    "from": "r2dii.physical.risk"
  },
  {
    "package": "janitor",
    "url": "https://github.com/sfirke/janitor",
    "via": ["r2dii.utils"],
    "from": "r2dii.utils"
  },
  {
    "package": "r2dii.colours",
    "url": "https://github.com/RMI-PACTA/r2dii.colours",
    "via": ["pacta.executive.summary"],
    "from": "pacta.executive.summary"
  },
  {
    "package": "r2dii.utils",
    "url": "https://github.com/2DegreesInvesting/r2dii.utils",
    "via": ["r2dii.physical.risk"],
    "from": "r2dii.physical.risk"
  }
]
